spotify_tools/__init__.py
spotify_tools/client.py
spotify_tools/exceptions.py
spotify_tools/logging.py
spotify_tools/playlists.py
spotify_tools/schemas.py
spotify_tools/search.py
spotify_tools/scripts/__init__.py
spotify_tools/scripts/shuffle_playlist.py
spotify_tools-0.0.2.dist-info/METADATA
spotify_tools-0.0.2.dist-info/WHEEL
spotify_tools-0.0.2.dist-info/licenses/LICENSE
spotify_tools-0.0.2.dist-info/RECORD
