Metadata-Version: 2.4
Name: spotify-tools
Version: 0.0.2
Summary: Tools for interacting with the Spotify API.
Author-email: Alex Richards <alex.richards006@gmail.com>
License-File: LICENSE
Keywords: spotify,tools
Requires-Python: >=3.10
Requires-Dist: fuzzywuzzy[speedup]
Requires-Dist: pydantic
Requires-Dist: pydantic-settings
Requires-Dist: spotipy
Requires-Dist: typer
